LICENSE
README.md
setup.py
EasyAI/__init__.py
EasyAI/TextClassifier/__init__.py
EasyAI/TextClassifier/base_classifier.py
EasyAI/TextClassifier/data_helper.py
EasyAI/TextClassifier/tokenizer.py
EasyAI/TextClassifier/fasttext/__init__.py
EasyAI/TextClassifier/fasttext/fasttext_classifier.py
EasyAI/TextClassifier/fasttext/data/__init__.py
EasyAI/TextClassifier/fasttext/data/build_dataset.py
EasyAI/TextClassifier/fasttext/models/__init__.py
EasyAI/TextClassifier/fasttext/models/fasttext_model.py
EasyAI/TextClassifier/ml/__init__.py
EasyAI/TextClassifier/ml/ml_classifier.py
EasyAI/TextClassifier/ml/text_cluster.py
EasyAI/TextClassifier/textcnn/__init__.py
EasyAI/TextClassifier/textcnn/textcnn_classifier.py
EasyAI/TextClassifier/textcnn/data/__init__.py
EasyAI/TextClassifier/textcnn/data/build_dataset.py
EasyAI/TextClassifier/textcnn/models/__init__.py
EasyAI/TextClassifier/textcnn/models/textcnn_model.py
EasyAI/TextClassifier/textrnn/__init__.py
EasyAI/TextClassifier/textrnn/textrnn_classifier.py
EasyAI/TextClassifier/textrnn/data/__init__.py
EasyAI/TextClassifier/textrnn/data/build_dataset.py
EasyAI/TextClassifier/textrnn/models/__init__.py
EasyAI/TextClassifier/textrnn/models/textrnn_model.py
EasyAI/TextClassifier/transformer/__init__.py
EasyAI/TextClassifier/transformer/bert_classifer.py
EasyAI/TextClassifier/transformer/models/__init__.py
EasyAI/TextClassifier/transformer/models/bert_classification_model.py
EasyAI/TextClassifier/transformer/models/bert_multi_label_classification_model.py
EasyAI/TextClassifier/transformer/utils/__init__.py
EasyAI/TextClassifier/transformer/utils/bert_classification_utils.py
EasyAI/common/__init__.py
EasyAI/common/logea.py
EasyAI/common/time_utils.py
EasyAIScaffolding.egg-info/PKG-INFO
EasyAIScaffolding.egg-info/SOURCES.txt
EasyAIScaffolding.egg-info/dependency_links.txt
EasyAIScaffolding.egg-info/top_level.txt