Metadata-Version: 2.1
Name: EasyAIScaffolding
Version: 1.0.0
Summary: A PyTorch-based AI development scaffolding
Home-page: https://github.com/mlshenkai/EasyAIScaffolding
Author: watcher shen
Author-email: watcher.shen@gmail.com
License: MIT License
Platform: all
License-File: LICENSE
